aqua_blue_hyperopt/__init__.py
aqua_blue_hyperopt/hyper.py
aqua_blue_hyperopt-0.0.4.dist-info/METADATA
aqua_blue_hyperopt-0.0.4.dist-info/WHEEL
aqua_blue_hyperopt-0.0.4.dist-info/licenses/LICENSE
aqua_blue_hyperopt-0.0.4.dist-info/RECORD
