Metadata-Version: 2.4
Name: aqua-blue-hyperopt
Version: 0.0.4
Summary: Hyperparameter optimization for aqua-blue models!
Project-URL: Homepage, https://github.com/lonelyneutrin0/aqua-blue-hyperopt
License-Expression: MIT
License-File: LICENSE
Keywords: aqua-blue,computing,optimization
Classifier: Programming Language :: Python :: 3.9
Classifier: Programming Language :: Python :: 3.10
Classifier: Programming Language :: Python :: 3.11
Classifier: Programming Language :: Python :: 3.12
Requires-Python: >=3.9
Requires-Dist: aqua-blue~=0.2.17
Requires-Dist: hyperopt~=0.2.7
Requires-Dist: numpy~=2.0.2
Provides-Extra: dev
Requires-Dist: hatchling~=1.27.0; extra == 'dev'
Requires-Dist: mypy~=1.13.0; extra == 'dev'
Requires-Dist: pdoc3~=0.11.5; extra == 'dev'
Requires-Dist: pytest~=8.0.2; extra == 'dev'
Requires-Dist: ruff~=0.9.4; extra == 'dev'
Provides-Extra: examples
Requires-Dist: matplotlib~=3.9.4; extra == 'examples'
